<?xml version="1.0"?>
<dc-workflow workflow_id="inscricao_workflow"
             title="inscricao_workflow" description=""
             state_variable="review_state"
             initial_state="novo">
 <permission>Delete objects</permission>
 <permission>Modify portal content</permission>
 <state state_id="em_confirmacao" title="Em Confirmacao">
  <exit-transition transition_id="cancelar_confirmacao"/>
  <exit-transition transition_id="finalizar_confirmacao"/>
  <permission-map name="Modify portal content"
                  acquired="False">
   <permission-role>Anonymous</permission-role>
   <permission-role>Owner</permission-role>
   <permission-role>Manager</permission-role>
  </permission-map>
 </state>
 <state state_id="novo" title="Sendo criado">
  <exit-transition transition_id="registrar"/>
  <exit-transition transition_id="salvar"/>
  <permission-map name="Delete objects" acquired="False">
   <permission-role>Anonymous</permission-role>
   <permission-role>Owner</permission-role>
   <permission-role>Manager</permission-role>
  </permission-map>
  <permission-map name="Modify portal content"
                  acquired="False">
   <permission-role>Anonymous</permission-role>
   <permission-role>Owner</permission-role>
   <permission-role>Manager</permission-role>
  </permission-map>
 </state>
 <state state_id="pre-inscrito" title="Pre-Inscrito">
  <exit-transition transition_id="confirmar"/>
  <exit-transition transition_id="iniciar_confirmacao"/>
  <permission-map name="Delete objects" acquired="False">
   <permission-role>Manager</permission-role>
  </permission-map>
  <permission-map name="Modify portal content"
                  acquired="False">
   <permission-role>Owner</permission-role>
   <permission-role>Manager</permission-role>
  </permission-map>
 </state>
 <state state_id="registrado" title="Registrado">
  <exit-transition transition_id="pagar"/>
  <permission-map name="Delete objects" acquired="False">
   <permission-role>Manager</permission-role>
  </permission-map>
  <permission-map name="Modify portal content"
                  acquired="False">
   <permission-role>Manager</permission-role>
  </permission-map>
 </state>
 <transition transition_id="cancelar_confirmacao"
             title="Cancelar Confirmacao"
             new_state="pre-inscrito" trigger="USER"
             before_script="" after_script="">
  <action url="" category="workflow">Cancelar Confirmacao</action>
  <guard>
  </guard>
 </transition>
 <transition transition_id="confirmar"
             title="Confirmar a Inscricao"
             new_state="registrado" trigger="USER"
             before_script=""
             after_script="enviaEmailConfirmacao">
  <action url="" category="workflow">Confirmar a Inscricao</action>
  <guard>
   <guard-role>Manager</guard-role>
   <guard-role>Owner</guard-role>
  </guard>
 </transition>
 <transition transition_id="finalizar_confirmacao"
             title="Finalizar Confirmacao"
             new_state="registrado" trigger="USER"
             before_script=""
             after_script="enviaEmailConfirmacao">
  <action url="" category="workflow">Finalizar Confirmacao</action>
  <guard>
  </guard>
 </transition>
 <transition transition_id="iniciar_confirmacao"
             title="Iniciar Confirmacao"
             new_state="em_confirmacao" trigger="USER"
             before_script="" after_script="">
  <action url="" category="workflow">Iniciar Confirmacao</action>
  <guard>
   <guard-expression>container/emInscricao</guard-expression>
  </guard>
 </transition>
 <transition transition_id="pagar" title="Pagar a Inscricao"
             new_state="registrado" trigger="USER"
             before_script="" after_script="marcaComoPaga">
  <action url="" category="workflow">Pagar a Inscricao</action>
  <guard>
   <guard-role>Manager</guard-role>
   <guard-expression>not:object/getPaga</guard-expression>
  </guard>
 </transition>
 <transition transition_id="registrar"
             title="Registrar Inscricao"
             new_state="registrado" trigger="USER"
             before_script=""
             after_script="enviaEmailConfirmacao">
  <action url="" category="workflow">Registrar Inscricao</action>
  <guard>
  </guard>
 </transition>
 <transition transition_id="salvar" title="Salvar Inscricao"
             new_state="pre-inscrito" trigger="USER"
             before_script="" after_script="">
  <action url="" category="workflow">Salvar Inscricao</action>
  <guard>
  </guard>
 </transition>
 <variable variable_id="action" for_catalog="False"
           for_status="True" update_always="True">
  <description>The last transition</description>
  <default>
   
   <expression>transition/getId|nothing</expression>
  </default>
  <guard>
  </guard>
 </variable>
 <variable variable_id="actor" for_catalog="False"
           for_status="True" update_always="True">
  <description>The ID of the user who performed the last transition</description>
  <default>
   
   <expression>user/getId</expression>
  </default>
  <guard>
  </guard>
 </variable>
 <variable variable_id="comments" for_catalog="False"
           for_status="True" update_always="True">
  <description>Comments about the last transition</description>
  <default>
   
   <expression>python:state_change.kwargs.get('comment', '')</expression>
  </default>
  <guard>
  </guard>
 </variable>
 <variable variable_id="review_history" for_catalog="False"
           for_status="False" update_always="False">
  <description>Provides access to workflow history</description>
  <default>
   
   <expression>state_change/getHistory</expression>
  </default>
  <guard>
   <guard-permission>Request review</guard-permission>
   <guard-permission>Review portal content</guard-permission>
  </guard>
 </variable>
 <variable variable_id="time" for_catalog="False"
           for_status="True" update_always="True">
  <description>Time of the last transition</description>
  <default>
   
   <expression>state_change/getDateTime</expression>
  </default>
  <guard>
  </guard>
 </variable>
 <script script_id="enviaEmailConfirmacao"
         type="External Method" filename=""
         module="PyConBrasil.workflow_scripts"
         function="enviaEmailConfirmacao"/>
 <script script_id="marcaComoPaga" type="External Method"
         filename="" module="PyConBrasil.workflow_scripts"
         function="marcaComoPaga"/>
</dc-workflow>
